MANIFEST.in
README.rst
setup.py
pybabel_htmlbars/__init__.py
pybabel_htmlbars/extractor.js
pybabel_htmlbars/extractor.py
pybabel_htmlbars/index.js
pybabel_htmlbars/package.json
pybabel_htmlbars.egg-info/PKG-INFO
pybabel_htmlbars.egg-info/SOURCES.txt
pybabel_htmlbars.egg-info/dependency_links.txt
pybabel_htmlbars.egg-info/entry_points.txt
pybabel_htmlbars.egg-info/requires.txt
pybabel_htmlbars.egg-info/top_level.txt
pybabel_htmlbars/test/data/template.hbs