Metadata-Version: 1.1
Name: pybabel-htmlbars
Version: 0.2.0
Summary: Pybabel HTMLBars gettext strings extractor
Home-page: https://github.com/eliksir/pybabel-htmlbars
Author: Eliksir AS
Author-email: code@e5r.no
License: BSD
Keywords: pybabel htmlbars gettext i18n
Platform: UNKNOWN
Classifier: Development Status :: 4 - Beta
Classifier: Intended Audience :: Developers
Classifier: License :: OSI Approved :: BSD License
Classifier: Programming Language :: JavaScript
Classifier: Programming Language :: Python
Classifier: Topic :: Software Development :: Internationalization
